get_rankings/__init__.py
get_rankings/get_rankings.py
get_rankings/hash_cache.py
get_rankings/tools.py
get_rankings-1.0.dist-info/AUTHORS
get_rankings-1.0.dist-info/LICENSE
get_rankings-1.0.dist-info/METADATA
get_rankings-1.0.dist-info/WHEEL
get_rankings-1.0.dist-info/entry_points.txt
get_rankings-1.0.dist-info/top_level.txt
get_rankings-1.0.dist-info/RECORD
