Metadata-Version: 2.1
Name: get-rankings
Version: 1.0
Summary: DBLP ranking using CORE Rank and SJR
Home-page: https://gitlab.irit.fr/sepia-pub/da-costa/get-rankings
Author: Georges Da Costa
Author-email: georges.da-costa@irit.fr
Classifier: Programming Language :: Python :: 3
Classifier: License :: OSI Approved :: GNU General Public License v3 or later (GPLv3+)
Classifier: Operating System :: OS Independent
Requires-Python: >=3.6
License-File: LICENSE
License-File: AUTHORS
Requires-Dist: BeautifulSoup4
Requires-Dist: argparse
Requires-Dist: datetime
Requires-Dist: lxml
Requires-Dist: numpy
Requires-Dist: pandas
Requires-Dist: parsedate
Requires-Dist: requests
Requires-Dist: tqdm
